CategoricalDataEncodingFunction/__init__.py
categoricaldataencoding-0.0.1.dist-info/LICENCE.txt
categoricaldataencoding-0.0.1.dist-info/METADATA
categoricaldataencoding-0.0.1.dist-info/WHEEL
categoricaldataencoding-0.0.1.dist-info/top_level.txt
categoricaldataencoding-0.0.1.dist-info/RECORD
