Metadata-Version: 2.1
Name: categoricaldataencoding
Version: 0.0.1
Summary: A package to encode the categorical data
Home-page: https://github.com/arvind444/categorical_data_encoding
Author: Arvindkumar
Author-email: arvindkumar1998ece@gmail.com
License: MIT
Keywords: categorical data encoding
Platform: UNKNOWN
Classifier: Programming Language :: Python :: 3
Classifier: License :: OSI Approved :: MIT License
Classifier: Operating System :: OS Independent
Requires-Python: >=3.6
License-File: LICENCE.txt
Requires-Dist: pandas
Requires-Dist: scikit-learn
